<?xml version="1.0" encoding="utf-8" ?>
<dwsync>
<file name="COPYING.txt" server="ftp.openintl.com" local="131308697016815280" remote="130577364000000000" Dst="0" />
<file name="Genericons.eot" server="ftp.openintl.com" local="131308697019321083" remote="130577364000000000" Dst="0" />
<file name="Genericons.svg" server="ftp.openintl.com" local="131308697021707451" remote="130577364000000000" Dst="0" />
<file name="Genericons.ttf" server="ftp.openintl.com" local="131308697024063568" remote="130577364000000000" Dst="0" />
<file name="Genericons.woff" server="ftp.openintl.com" local="131308697024940654" remote="130577364000000000" Dst="0" />
<file name="LICENSE.txt" server="ftp.openintl.com" local="131308697029642894" remote="130577364000000000" Dst="0" />
<file name="README.md" server="ftp.openintl.com" local="131308697029703061" remote="130577364000000000" Dst="0" />
<file name="genericons.css" server="ftp.openintl.com" local="131308697032931217" remote="130626612000000000" Dst="0" />
</dwsync>